binance_sdk_spot/__init__.py
binance_sdk_spot/metadata.py
binance_sdk_spot/rest_api/__init__.py
binance_sdk_spot/rest_api/api/__init__.py
binance_sdk_spot/rest_api/api/account_api.py
binance_sdk_spot/rest_api/api/general_api.py
binance_sdk_spot/rest_api/api/market_api.py
binance_sdk_spot/rest_api/api/trade_api.py
binance_sdk_spot/rest_api/models/__init__.py
binance_sdk_spot/rest_api/models/account_commission_response.py
binance_sdk_spot/rest_api/models/account_commission_response_discount.py
binance_sdk_spot/rest_api/models/account_commission_response_special_commission.py
binance_sdk_spot/rest_api/models/account_commission_response_standard_commission.py
binance_sdk_spot/rest_api/models/account_commission_response_tax_commission.py
binance_sdk_spot/rest_api/models/agg_trades_response.py
binance_sdk_spot/rest_api/models/agg_trades_response_inner.py
binance_sdk_spot/rest_api/models/all_order_list_response.py
binance_sdk_spot/rest_api/models/all_order_list_response_inner.py
binance_sdk_spot/rest_api/models/all_order_list_response_inner_orders_inner.py
binance_sdk_spot/rest_api/models/all_orders_response.py
binance_sdk_spot/rest_api/models/all_orders_response_inner.py
binance_sdk_spot/rest_api/models/asset_filters.py
binance_sdk_spot/rest_api/models/avg_price_response.py
binance_sdk_spot/rest_api/models/delete_open_orders_response.py
binance_sdk_spot/rest_api/models/delete_open_orders_response_inner.py
binance_sdk_spot/rest_api/models/delete_order_list_response.py
binance_sdk_spot/rest_api/models/delete_order_list_response_order_reports_inner.py
binance_sdk_spot/rest_api/models/delete_order_list_response_orders_inner.py
binance_sdk_spot/rest_api/models/delete_order_response.py
binance_sdk_spot/rest_api/models/depth_response.py
binance_sdk_spot/rest_api/models/enums.py
binance_sdk_spot/rest_api/models/exchange_filters.py
binance_sdk_spot/rest_api/models/exchange_info_response.py
binance_sdk_spot/rest_api/models/exchange_info_response_symbols_inner.py
binance_sdk_spot-6.3.0.dist-info/METADATA
binance_sdk_spot-6.3.0.dist-info/WHEEL
binance_sdk_spot-6.3.0.dist-info/licenses/LICENCE
binance_sdk_spot-6.3.0.dist-info/RECORD
