Metadata-Version: 2.4
Name: binance-sdk-spot
Version: 6.3.0
Summary: Official Binance Spot SDK - A lightweight library that provides a convenient interface to Binance's Spot REST API, WebSocket API and WebSocket Streams.
License: MIT
License-File: LICENCE
Author: Binance
Requires-Python: >=3.9,<3.15
Classifier: License :: OSI Approved :: MIT License
Classifier: Programming Language :: Python :: 3
Classifier: Programming Language :: Python :: 3.9
Classifier: Programming Language :: Python :: 3.10
Classifier: Programming Language :: Python :: 3.11
Classifier: Programming Language :: Python :: 3.12
Classifier: Programming Language :: Python :: 3.13
Classifier: Programming Language :: Python :: 3.14
Provides-Extra: dev
Requires-Dist: aiohttp (>=3.9,<4.0)
Requires-Dist: binance-common (==3.4.1)
Requires-Dist: black (>=25.1.0,<26.0.0)
Requires-Dist: pycryptodome (>=3.17,<4.0)
Requires-Dist: pydantic (>=2.10.0)
Requires-Dist: pytest (>=6.2.5) ; extra == "dev"
Requires-Dist: requests (>=2.31.0)
Requires-Dist: ruff (>=0.12.0,<0.13.0)
Requires-Dist: websocket-client (>=1.6.3)
Requires-Dist: websockets (>=15.0.1,<16.0.0)
